beancount_oneliner/oneliner.py
beancount_oneliner-1.3.1.dist-info/licenses/LICENSE
beancount_oneliner-1.3.1.dist-info/METADATA
beancount_oneliner-1.3.1.dist-info/WHEEL
beancount_oneliner-1.3.1.dist-info/top_level.txt
beancount_oneliner-1.3.1.dist-info/RECORD
