Metadata-Version: 2.4
Name: beancount_oneliner
Version: 1.3.1
Summary: Plugin for Beancount to write oneliner transaction entries.
Home-page: https://github.com/Akuukis/beancount_oneliner
Author: Kalvis 'Akuukis' Kalnins
Author-email: akuukis@kalvis.lv
License: GPLv3
Requires: beancount (>=2.0)
License-File: LICENSE
Dynamic: author
Dynamic: author-email
Dynamic: description
Dynamic: description-content-type
Dynamic: home-page
Dynamic: license
Dynamic: license-file
Dynamic: requires
Dynamic: summary
